//
// Created by GentlyGuitar on 11/5/2016.
//

#include "SysUtil.h"
#include "../interpreter/Bytecode.h"

std::map<char, JBCMeta*> SysUtil::bcdict;

void SysUtil::init_bcdict() {
//    bcdict[0x32] = "aaload";
//    bcdict[0x53] = "aastore";
//    bcdict[0x01] = "aconst_null";
//    bcdict[0x19] = "aload";
//    bcdict[0x2a] = "do_aload_0";
//    bcdict[0x2b] = "aload_1";
//    bcdict[0x2c] = "aload_2";
//    bcdict[0x2d] = "aload_3";
//    bcdict[0xbd] = "anewarray";
//    bcdict[0xb0] = "areturn";
//    bcdict[0xbe] = "arraylength";
//    bcdict[0x3a] = "astore";
//    bcdict[0x4b] = "astore_0";
//    bcdict[0x4c] = "astore_1";
//    bcdict[0x4d] = "astore_2";
//    bcdict[0x4e] = "astore_3";
//    bcdict[0xbf] = "athrow";
//    bcdict[0x33] = "baload";
//    bcdict[0x54] = "bastore";
//    bcdict[0x10] = "bipush";
//    bcdict[0xca] = "breakpoint";
//    bcdict[0x34] = "caload";
//    bcdict[0x55] = "castore";
//    bcdict[0xc0] = "checkcast";
//    bcdict[0x90] = "d2f";
//    bcdict[0x8e] = "d2i";
//    bcdict[0x8f] = "d2l";
//    bcdict[0x63] = "dadd";
//    bcdict[0x31] = "daload";
//    bcdict[0x52] = "dastore";
//    bcdict[0x98] = "dcmpg";
//    bcdict[0x97] = "dcmpl";
//    bcdict[0x0e] = "dconst_0";
//    bcdict[0x0f] = "dconst_1";
//    bcdict[0x6f] = "ddiv";
//    bcdict[0x18] = "dload";
//    bcdict[0x26] = "dload_0";
//    bcdict[0x27] = "dload_1";
//    bcdict[0x28] = "dload_2";
//    bcdict[0x29] = "dload_3";
//    bcdict[0x6b] = "dmul";
//    bcdict[0x77] = "dneg";
//    bcdict[0x73] = "drem";
//    bcdict[0xaf] = "dreturn";
//    bcdict[0x39] = "dstore";
//    bcdict[0x47] = "dstore_0";
//    bcdict[0x48] = "dstore_1";
//    bcdict[0x49] = "dstore_2";
//    bcdict[0x4a] = "dstore_3";
//    bcdict[0x67] = "dsub";
//    bcdict[0x59] = "dup";
//    bcdict[0x5a] = "dup_x1";
//    bcdict[0x5b] = "dup_x2";
//    bcdict[0x5c] = "dup2";
//    bcdict[0x5d] = "dup2_x1";
//    bcdict[0x5e] = "dup2_x2";
//    bcdict[0x8d] = "f2d";
//    bcdict[0x8b] = "f2i";
//    bcdict[0x8c] = "f2l";
//    bcdict[0x62] = "fadd";
//    bcdict[0x30] = "faload";
//    bcdict[0x51] = "fastore";
//    bcdict[0x96] = "fcmpg";
//    bcdict[0x95] = "fcmpl";
//    bcdict[0x0b] = "fconst_0";
//    bcdict[0x0c] = "fconst_1";
//    bcdict[0x0d] = "fconst_2";
//    bcdict[0x6e] = "fdiv";
//    bcdict[0x17] = "fload";
//    bcdict[0x22] = "fload_0";
//    bcdict[0x23] = "fload_1";
//    bcdict[0x24] = "fload_2";
//    bcdict[0x25] = "fload_3";
//    bcdict[0x6a] = "fmul";
//    bcdict[0x76] = "fneg";
//    bcdict[0x72] = "frem";
//    bcdict[0xae] = "freturn";
//    bcdict[0x38] = "fstore";
//    bcdict[0x43] = "fstore_0";
//    bcdict[0x44] = "fstore_1";
//    bcdict[0x45] = "fstore_2";
//    bcdict[0x46] = "fstore_3";
//    bcdict[0x66] = "fsub";
//    bcdict[0xb4] = "getfield";
//    bcdict[0xb2] = "getstatic";
//    bcdict[0xa7] = "goto";
//    bcdict[0xc8] = "goto_w";
//    bcdict[0x91] = "i2b";
//    bcdict[0x92] = "i2c";
//    bcdict[0x87] = "i2d";
//    bcdict[0x86] = "i2f";
//    bcdict[0x85] = "i2l";
//    bcdict[0x93] = "i2s";
//    bcdict[0x60] = "iadd";
//    bcdict[0x2e] = "iaload";
//    bcdict[0x7e] = "iand";
//    bcdict[0x4f] = "iastore";
//    bcdict[0x02] = "iconst_m1";
//    bcdict[0x03] = "iconst_0";
//    bcdict[0x04] = "iconst_1";
//    bcdict[0x05] = "iconst_2";
//    bcdict[0x06] = "iconst_3";
//    bcdict[0x07] = "iconst_4";
//    bcdict[0x08] = "iconst_5";
//    bcdict[0x6c] = "idiv";
//    bcdict[0xa5] = "if_acmpeq";
//    bcdict[0xa6] = "if_acmpne";
//    bcdict[0x9f] = "if_icmpeq";
//    bcdict[0xa2] = "if_icmpge";
//    bcdict[0xa3] = "if_icmpgt";
//    bcdict[0xa4] = "if_icmple";
//    bcdict[0xa1] = "if_icmplt";
//    bcdict[0xa0] = "if_icmpne";
//    bcdict[0x99] = "ifeq";
//    bcdict[0x9c] = "ifge";
//    bcdict[0x9d] = "ifgt";
//    bcdict[0x9e] = "ifle";
//    bcdict[0x9b] = "iflt";
//    bcdict[0x9a] = "ifne";
//    bcdict[0xc7] = "ifnonnull";
//    bcdict[0xc6] = "ifnull";
//    bcdict[0x84] = "iinc";
//    bcdict[0x15] = "iload";
//    bcdict[0x1a] = "iload_0";
//    bcdict[0x1b] = "iload_1";
//    bcdict[0x1c] = "iload_2";
//    bcdict[0x1d] = "iload_3";
//    bcdict[0xfe] = "impdep1";
//    bcdict[0xff] = "impdep2";
//    bcdict[0x68] = "imul";
//    bcdict[0x74] = "ineg";
//    bcdict[0xc1] = "instanceof";
//    bcdict[0xba] = "invokedynamic";
//    bcdict[0xb9] = "invokeinterface";
//    bcdict[0xb7] = "invokespecial";
//    bcdict[0xb8] = "invokestatic";
//    bcdict[0xb6] = "invokevirtual";
//    bcdict[0x80] = "ior";
//    bcdict[0x70] = "irem";
//    bcdict[0xac] = "ireturn";
//    bcdict[0x78] = "ishl";
//    bcdict[0x7a] = "ishr";
//    bcdict[0x36] = "istore";
//    bcdict[0x3b] = "istore_0";
//    bcdict[0x3c] = "istore_1";
//    bcdict[0x3d] = "istore_2";
//    bcdict[0x3e] = "istore_3";
//    bcdict[0x64] = "isub";
//    bcdict[0x7c] = "iushr";
//    bcdict[0x82] = "ixor";
//    bcdict[0xa8] = "jsr";
//    bcdict[0xc9] = "jsr_w";
//    bcdict[0x8a] = "l2d";
//    bcdict[0x89] = "l2f";
//    bcdict[0x88] = "l2i";
//    bcdict[0x61] = "ladd";
//    bcdict[0x2f] = "laload";
//    bcdict[0x7f] = "land";
//    bcdict[0x50] = "lastore";
//    bcdict[0x94] = "lcmp";
//    bcdict[0x09] = "lconst_0";
//    bcdict[0x0a] = "lconst_1";
//    bcdict[0x12] = "ldc";
//    bcdict[0x13] = "ldc_w";
//    bcdict[0x14] = "ldc2_w";
//    bcdict[0x6d] = "ldiv";
//    bcdict[0x16] = "lload";
//    bcdict[0x1e] = "lload_0";
//    bcdict[0x1f] = "lload_1";
//    bcdict[0x20] = "lload_2";
//    bcdict[0x21] = "lload_3";
//    bcdict[0x69] = "lmul";
//    bcdict[0x75] = "lneg";
//    bcdict[0xab] = "lookupswitch";
//    bcdict[0x81] = "lor";
//    bcdict[0x71] = "lrem";
//    bcdict[0xad] = "lreturn";
//    bcdict[0x79] = "lshl";
//    bcdict[0x7b] = "lshr";
//    bcdict[0x37] = "lstore";
//    bcdict[0x3f] = "lstore_0";
//    bcdict[0x40] = "lstore_1";
//    bcdict[0x41] = "lstore_2";
//    bcdict[0x42] = "lstore_3";
//    bcdict[0x65] = "lsub";
//    bcdict[0x7d] = "lushr";
//    bcdict[0x83] = "lxor";
//    bcdict[0xc2] = "monitorenter";
//    bcdict[0xc3] = "monitorexit";
//    bcdict[0xc5] = "multianewarray";
//    bcdict[0xbb] = "new";
//    bcdict[0xbc] = "newarray";
//    bcdict[0x00] = "nop";
//    bcdict[0x57] = "pop";
//    bcdict[0x58] = "pop2";
//    bcdict[0xb5] = "putfield";
//    bcdict[0xb3] = "putstatic";
//    bcdict[0xa9] = "ret";
//    bcdict[0xb1] = "return";
//    bcdict[0x35] = "saload";
//    bcdict[0x56] = "sastore";
//    bcdict[0x11] = "sipush";
//    bcdict[0x5f] = "swap";
//    bcdict[0xaa] = "tableswitch";
//    bcdict[0xc4] = "wide";
    bcdict[0xbb] = new JBCMeta(Bytecode::BC_new, "new", 2);
    bcdict[0x59] = new JBCMeta(Bytecode::BC_dup, "dup", 0);
    bcdict[0xb7] = new JBCMeta(Bytecode::BC_invokespecial, "invokespecial", 2);
}